{
	"result":[
	{
		"img_src":["images/nav/pic_001.png","images/nav/pic_002.png","images/nav/pic_003.png","images/nav/pic_004.png","images/nav/pic_005.png","images/nav/pic_006.png"],
		"tit":["被枕","床品","地垫","灯具","家具","舒坐"]
	},
	{
		"img_src":["images/nav/pic_007.png","images/nav/pic_008.png","images/nav/pic_009.png","images/nav/pic_010.png","images/nav/pic_011.png","images/nav/pic_012.png","images/nav/pic_013.png","images/nav/pic_014.png"],
		"tit":["锅具","刀铲","功能厨具","餐具","背壶","茶具","保鲜","清洁"]
	},
	{
		"img_src":["images/nav/pic_015.png","images/nav/pic_016.png","images/nav/pic_017.png","images/nav/pic_018.png","images/nav/pic_019.png","images/nav/pic_020.png"],
		"tit":["功能箱包","双肩包","单肩包","鞋","拖鞋","配饰"]
	},
	{
		"img_src":["images/nav/pic_021.png","images/nav/pic_022.png","images/nav/pic_023.png","images/nav/pic_024.png","images/nav/pic_025.png","images/nav/pic_026.png"],
		"tit":["内裤","内衣","袜子","家居服","T恤","衬衫"]
	},
	{
		"img_src":["images/nav/pic_027.png","images/nav/pic_028.png","images/nav/pic_029.png","images/nav/pic_030.png","images/nav/pic_031.png","images/nav/pic_032.png","images/nav/pic_033.png"],
		"tit":["护肤","美妆","香薰","毛巾","镜梳","洗浴","用具"]
	},
	{
		"img_src":["images/nav/pic_034.png","images/nav/pic_035.png","images/nav/pic_036.png","images/nav/pic_037.png","images/nav/pic_038.png","images/nav/pic_039.png"],
		"tit":["服饰","妈咪","寝居","玩具","用品","喂养"]
	},
	{
		"img_src":["images/nav/pic_040.png","images/nav/pic_041.png","images/nav/pic_042.png","images/nav/pic_043.png","images/nav/pic_044.png"],
		"tit":["文具","收纳","旅行","雨具","口罩"]
	},
	{
		"img_src":["images/nav/pic_045.png","images/nav/pic_046.png","images/nav/pic_047.png","images/nav/pic_048.png","images/nav/pic_049.png"],
		"tit":["糕点","小食","炒货","对饮","食材"]
	},
	{
		"img_src":["images/nav/pic_050.png","images/nav/pic_051.png","images/nav/pic_052.png"],
		"tit":["宠物","户外","夏日甜心"]
	}
	]
}





















